mcp_bitbucket/__init__.py
mcp_bitbucket/__main__.py
mcp_bitbucket/server.py
iflow_mcp_mcp_bitbucket-0.1.0.dist-info/METADATA
iflow_mcp_mcp_bitbucket-0.1.0.dist-info/WHEEL
iflow_mcp_mcp_bitbucket-0.1.0.dist-info/entry_points.txt
iflow_mcp_mcp_bitbucket-0.1.0.dist-info/RECORD
