Metadata-Version: 2.4
Name: iflow-mcp_mcp-bitbucket
Version: 0.1.0
Summary: MCP server for bitbucket python API
Requires-Python: >=3.13
Requires-Dist: atlassian-python-api>=3.41.4
Requires-Dist: mcp>=1.2.0
Requires-Dist: requests>=2.31.0
